localuf/__init__.py
localuf/_base_classes.py
localuf/_determinants.py
localuf/_pairs.py
localuf/_schemes.py
localuf/codes.py
localuf/constants.py
localuf/data_processors.py
localuf/type_aliases.py
localuf/decoders/__init__.py
localuf/decoders/_base_uf.py
localuf/decoders/buf.py
localuf/decoders/mwpm.py
localuf/decoders/node_buf.py
localuf/decoders/node_uf.py
localuf/decoders/policies.py
localuf/decoders/uf.py
localuf/decoders/luf/__init__.py
localuf/decoders/luf/alternatives.py
localuf/decoders/luf/constants.py
localuf/decoders/luf/main.py
localuf/decoders/snowflake/__init__.py
localuf/decoders/snowflake/constants.py
localuf/decoders/snowflake/main.py
localuf/noise/__init__.py
localuf/noise/_multiset_handler.py
localuf/noise/forcers.py
localuf/noise/main.py
localuf/plot/__init__.py
localuf/plot/accuracy.py
localuf/plot/runtime.py
localuf/sim/__init__.py
localuf/sim/_height_calculator.py
localuf/sim/latency.py
localuf/sim/runtime.py
localuf/sim/accuracy/__init__.py
localuf/sim/accuracy/monte_carlo.py
localuf-3.4.3.dist-info/METADATA
localuf-3.4.3.dist-info/WHEEL
localuf-3.4.3.dist-info/licenses/LICENSE
localuf-3.4.3.dist-info/RECORD
